Metadata-Version: 1.0
Name: oldmatplotlib
Version: 0.1
Summary: Package for Lab 2...
Home-page: http://example.com
Author: me me me
Author-email: wooooah@gmail.com
License: UNKNOWN
Platform: UNKNOWN
